djeese_fs-0.1.21.dist-info/DESCRIPTION.rst
djeese_fs-0.1.21.dist-info/entry_points.txt
djeese_fs-0.1.21.dist-info/METADATA
djeese_fs-0.1.21.dist-info/metadata.json
djeese_fs-0.1.21.dist-info/RECORD
djeese_fs-0.1.21.dist-info/top_level.txt
djeese_fs-0.1.21.dist-info/WHEEL
fs/__init__.py
fs/cli.py
fs/client.py
fs/datadog.py
fs/django_storage.py
fs/security.py
fs/server.py
fs/tests.py
fs/utils.py
