Metadata-Version: 2.0
Name: djeese-fs
Version: 0.1.21
Summary: A twisted based daemon file system.
Home-page: https://github.com/aldryncore/djeese-fs
Author: Jonas Obrist
Author-email: ojiidotch@gmail.com
License: BSD
Platform: OS Independent
Requires-Dist: argparse (>=1.2.1)
Requires-Dist: certifi (>=0.0.8)
Requires-Dist: chardet (>=1.0.1)
Provides-Extra: server
Requires-Dist: Twisted (>=12.0.0); extra == 'server'
Requires-Dist: zope.interface (>=3.8.0); extra == 'server'
